[
    {
        "name": "Kamrul hasan",
        "e-mail": "kamrul@gmail.com",
        "username": "Avi",
        "password": "1234567@",
        "gender": "male",
        "peraddress": "Sherpur,",
        "paddress": "Bogra",
        "city": "Bogra",
        "phone": "01711222300"
    },
    {
        "name": "Fahim",
        "e-mail": "kamrul@gmail.com",
        "username": "Avi",
        "password": "1234567@",
        "gender": "male",
        "peraddress": "Sherpur,",
        "paddress": "Bogra",
        "city": "Bogra",
        "phone": "01711222300"
    },
    {
        "name": "Hasibul pagol",
        "e-mail": "kamrul@gmail.com",
        "username": "Avi",
        "password": "1234567@",
        "gender": "male",
        "peraddress": "Sherpur,",
        "paddress": "Bogra",
        "city": "Bogra",
        "phone": "01711222300"
    },
    {
        "name": "Ruhin Tatu",
        "e-mail": "tatu@gmail.com",
        "username": "Avi",
        "password": "1234567@",
        "gender": "male",
        "peraddress": "Sherpur,",
        "paddress": "Bogra",
        "city": "Bogra",
        "phone": "01725727472"
    }

]